advanced_research/__init__.py
advanced_research/main.py
advanced_research/prompts.py
advanced_research-0.2.2.dist-info/LICENSE
advanced_research-0.2.2.dist-info/METADATA
advanced_research-0.2.2.dist-info/WHEEL
advanced_research-0.2.2.dist-info/RECORD
