Metadata-Version: 2.3
Name: advanced-research
Version: 0.2.2
Summary: Advanced Multi-Agent Research System - Enhanced implementation of Anthropic's orchestrator-worker pattern with 90.2% performance improvement over single-agent systems
License: MIT
Keywords: artificial intelligence,multi-agent systems,research automation,anthropic,orchestrator-worker pattern,parallel execution,web search,citation generation,llm-as-judge
Author: Kye Gomez
Author-email: kye@swarms.world
Requires-Python: >=3.10
Classifier: Development Status :: 4 - Beta
Classifier: Intended Audience :: Developers
Classifier: Intended Audience :: Science/Research
Classifier: License :: OSI Approved :: MIT License
Classifier: Programming Language :: Python :: 3
Classifier: Programming Language :: Python :: 3.10
Classifier: Programming Language :: Python :: 3.11
Classifier: Programming Language :: Python :: 3.12
Classifier: Programming Language :: Python :: 3.13
Classifier: Topic :: Internet :: WWW/HTTP :: Indexing/Search
Classifier: Topic :: Scientific/Engineering :: Artificial Intelligence
Classifier: Topic :: Text Processing :: Markup :: Markdown
Requires-Dist: httpx
Requires-Dist: loguru
Requires-Dist: orjson
Requires-Dist: pydantic
Requires-Dist: python-dotenv
Requires-Dist: requests
Requires-Dist: swarms
Requires-Dist: swarms-tools
Project-URL: Documentation, https://github.com/The-Swarm-Corporation/AdvancedResearch/blob/main/Docs.md
Project-URL: Homepage, https://github.com/The-Swarm-Corporation/AdvancedResearch
Project-URL: Repository, https://github.com/The-Swarm-Corporation/AdvancedResearch
